{
  "localizedName": "Ragged Wastelands",
  "description": "Beyond the remote islands are desolated coastline wastes. Centuries of harsh winds and scorching temperatures have molded this shore into a withered wasteland. Silver, which is rare on Serpulo, is abnormally abundant in this sector. Gather as much of it as possible.\n\nThe enemy has stationed many unique naval units in this location. Eradicate them and research these new fighting units.",
  "sector": 97,
  "captureWave": 20,
  "difficulty": 3,
  "planet": "serpulo",
  "research": {
    "parent": "windsweptIslands",
    "objectives": [
      "retusa"
    ]
  }
}
